odoo8_addon_runbot_pylint-8.0.1.0.0-py2.7-nspkg.pth
odoo_addons/runbot_pylint/__openerp__.py
odoo_addons/runbot_pylint/__init__.py
odoo_addons/runbot_pylint/README.rst
odoo_addons/runbot_pylint/models/runbot_build.py
odoo_addons/runbot_pylint/models/__init__.py
odoo_addons/runbot_pylint/models/runbot_repo.py
odoo_addons/runbot_pylint/views/runbot_pylint_view.xml
odoo8_addon_runbot_pylint-8.0.1.0.0.dist-info/top_level.txt
odoo8_addon_runbot_pylint-8.0.1.0.0.dist-info/WHEEL
odoo8_addon_runbot_pylint-8.0.1.0.0.dist-info/RECORD
odoo8_addon_runbot_pylint-8.0.1.0.0.dist-info/metadata.json
odoo8_addon_runbot_pylint-8.0.1.0.0.dist-info/DESCRIPTION.rst
odoo8_addon_runbot_pylint-8.0.1.0.0.dist-info/METADATA
odoo8_addon_runbot_pylint-8.0.1.0.0.dist-info/namespace_packages.txt
